LICENSE
MANIFEST.in
README.md
setup.py
quartz/__init__.py
quartz/cli.py
quartz/models.py
quartz/service.py
quartz.egg-info/PKG-INFO
quartz.egg-info/SOURCES.txt
quartz.egg-info/dependency_links.txt
quartz.egg-info/entry_points.txt
quartz.egg-info/requires.txt
quartz.egg-info/top_level.txt
quartz/handlers/__init__.py
quartz/handlers/page_handlers.py
quartz/html/static/css/animate.css
quartz/html/static/css/c3.min.css
quartz/html/static/css/materialize.min.css
quartz/html/static/js/bootstrap-notify.min.js
quartz/html/static/js/c3.min.js
quartz/html/static/js/d3.v3.min.js
quartz/html/static/js/jquery-3.1.1.min.js
quartz/html/static/js/materialize.min.js
quartz/html/static/js/pymicroservice.js
quartz/html/templates/about.html
quartz/html/templates/category_view.html
quartz/html/templates/create_category.html
quartz/html/templates/create_project.html
quartz/html/templates/dashboard.html
quartz/html/templates/docs.html
quartz/html/templates/events.html
quartz/html/templates/events_import_data.html
quartz/html/templates/events_statistics.html
quartz/html/templates/plots.html
quartz/html/templates/plots_img.html
quartz/html/templates/project_edit.html
quartz/html/templates/project_view.html
quartz/html/templates/projects.html
quartz/html/templates/status.html
quartz/html/templates/template.html
quartz/lib/__init__.py
quartz/lib/pyplot_charter.py
quartz/lib/query.py
quartz/lib/util.py
quartz/lib/importers/__init__.py
quartz/lib/importers/base_importer.py
quartz/lib/importers/json_importer.py
quartz/lib/importers/xml_importer.py
quartz/lib/utilscripts/__init__.py
quartz/lib/utilscripts/generate_chart.py
tests/__init__.py
tests/test_query.py