Metadata-Version: 1.0
Name: quartz
Version: 0.0.1.dev0
Summary: Track events in other applications
Home-page: UNKNOWN
Author: Vlad Calin
Author-email: vlad.s.calin@gmail.com
License: UNKNOWN
Platform: UNKNOWN
